tests/__init__.py
tests/test_breed.py
tests/test_cut.py
tests/test_utils.py
tree_storage/__init__.py
tree_storage/__version__.py
tree_storage/exceptions.py
tree_storage/tree.py
tree_storage/utils.py
tree_storage-0.1.11.dist-info/LICENSE
tree_storage-0.1.11.dist-info/METADATA
tree_storage-0.1.11.dist-info/WHEEL
tree_storage-0.1.11.dist-info/top_level.txt
tree_storage-0.1.11.dist-info/RECORD
