Metadata-Version: 2.1
Name: tree-storage
Version: 0.1.11
Summary: Tree hash-storage files
Home-page: UNKNOWN
Author: Valerii Duz
Author-email: duz.valera.od@ex.ua
License: UNKNOWN
Platform: UNKNOWN
Classifier: Programming Language :: Python :: 3.4
Classifier: Programming Language :: Python :: 3.5
Classifier: Programming Language :: Python :: 3.6
Classifier: License :: OSI Approved :: MIT License
Classifier: Operating System :: OS Independent
